MANIFEST.in
setup.py
django_bootstrap_mockups.egg-info/PKG-INFO
django_bootstrap_mockups.egg-info/SOURCES.txt
django_bootstrap_mockups.egg-info/dependency_links.txt
django_bootstrap_mockups.egg-info/not-zip-safe
django_bootstrap_mockups.egg-info/requires.txt
django_bootstrap_mockups.egg-info/top_level.txt
styleguide/__init__.py
styleguide/forms.py
styleguide/models.py
styleguide/urls.py
styleguide/utils.py
styleguide/views.py
styleguide/management/__init__.py
styleguide/management/commands/__init__.py
styleguide/management/commands/compilescss.py
styleguide/management/commands/watchscss.py
styleguide/static/bootstrap_docs/assets/css/docs.css
styleguide/static/bootstrap_docs/assets/css/docs.min.css
styleguide/static/bootstrap_docs/assets/css/pygments-manni.css
styleguide/static/bootstrap_docs/assets/ico/apple-touch-icon-144-precomposed.png
styleguide/static/bootstrap_docs/assets/ico/favicon.ico
styleguide/static/bootstrap_docs/assets/img/components.png
styleguide/static/bootstrap_docs/assets/img/devices.png
styleguide/static/bootstrap_docs/assets/img/sass-less.png
styleguide/static/bootstrap_docs/assets/js/application.js
styleguide/static/bootstrap_docs/assets/js/customize.min.js
styleguide/static/bootstrap_docs/assets/js/customizer.js
styleguide/static/bootstrap_docs/assets/js/docs.min.js
styleguide/static/bootstrap_docs/assets/js/ie8-responsive-file-warning.js
styleguide/static/bootstrap_docs/assets/js/raw-files.min.js
styleguide/static/bootstrap_docs/assets/js/vendor/blob.js
styleguide/static/bootstrap_docs/assets/js/vendor/filesaver.js
styleguide/static/bootstrap_docs/assets/js/vendor/holder.js
styleguide/static/bootstrap_docs/assets/js/vendor/jszip.min.js
styleguide/static/bootstrap_docs/assets/js/vendor/less.min.js
styleguide/static/bootstrap_docs/assets/js/vendor/uglify.min.js
styleguide/static/bootstrap_docs/dist/css/bootstrap-theme.css.map
styleguide/static/bootstrap_docs/dist/css/bootstrap-theme.min.css
styleguide/static/bootstrap_docs/dist/css/bootstrap.css.map
styleguide/static/bootstrap_docs/dist/css/bootstrap.min.css
styleguide/static/bootstrap_docs/dist/fonts/glyphicons-halflings-regular.eot
styleguide/static/bootstrap_docs/dist/fonts/glyphicons-halflings-regular.svg
